nautobot_mcp/__init__.py
nautobot_mcp/management/__init__.py
nautobot_mcp/management/commands/__init__.py
nautobot_mcp/management/commands/start_mcp_dev_server.py
nautobot_mcp/management/commands/start_mcp_server.py
nautobot_mcp/migrations/0001_create_mcp_tool.py
nautobot_mcp/migrations/__init__.py
nautobot_mcp/models.py
nautobot_mcp/navigation.py
nautobot_mcp/scripts/mcp_client_check.py
nautobot_mcp/templates/nautobot_mcp/tools.html
nautobot_mcp/tests/__init__.py
nautobot_mcp/tools/__init__.py
nautobot_mcp/tools/circuit_tools.py
nautobot_mcp/tools/device_tools.py
nautobot_mcp/tools/interface_tools.py
nautobot_mcp/tools/ipam_tools.py
nautobot_mcp/tools/location_tools.py
nautobot_mcp/tools/platform_tools.py
nautobot_mcp/tools/registry.py
nautobot_mcp/urls.py
nautobot_mcp/utilities/__init__.py
nautobot_mcp/utilities/logger.py
nautobot_mcp/views.py
nautobot_mcp-0.1.2.dist-info/LICENSE
nautobot_mcp-0.1.2.dist-info/METADATA
nautobot_mcp-0.1.2.dist-info/WHEEL
nautobot_mcp-0.1.2.dist-info/RECORD
