Metadata-Version: 2.3
Name: nautobot-mcp
Version: 0.1.2
Summary: Nautobot MCP
License: Apache-2.0
Author: Geury Torres
Author-email: geuryt@yahoo.com
Requires-Python: >=3.8,<4.0
Classifier: Framework :: Django
Classifier: Intended Audience :: System Administrators
Classifier: License :: OSI Approved :: Apache Software License
Classifier: Programming Language :: Python :: 3
Classifier: Programming Language :: Python :: 3.8
Classifier: Programming Language :: Python :: 3.9
Classifier: Programming Language :: Python :: 3.10
Classifier: Programming Language :: Python :: 3.11
Classifier: Programming Language :: Python :: 3.12
Classifier: Programming Language :: Python :: 3.13
Requires-Dist: mcp (>=1.6.0,<2.0.0)
Project-URL: Repository, https://github.com/gt732/nautobot-app-mcp
